cfdppy/__init__.py
cfdppy/crc.py
cfdppy/defs.py
cfdppy/exceptions.py
cfdppy/filestore.py
cfdppy/mib.py
cfdppy/request.py
cfdppy/restricted_filestore.py
cfdppy/user.py
cfdppy/handler/__init__.py
cfdppy/handler/common.py
cfdppy/handler/defs.py
cfdppy/handler/dest.py
cfdppy/handler/source.py
cfdp_py-0.6.0.dist-info/METADATA
cfdp_py-0.6.0.dist-info/WHEEL
cfdp_py-0.6.0.dist-info/licenses/LICENSE
cfdp_py-0.6.0.dist-info/RECORD
