Metadata-Version: 2.4
Name: cfdp-py
Version: 0.6.0
Summary: Library for high level CCSDS File Delivery Protocol (CFDP) components
Project-URL: Homepage, https://github.com/us-irs/cfdp-py
Author-email: Robin Mueller <robin.mueller.m@pm.me>
License-Expression: Apache-2.0
License-File: LICENSE
Keywords: ccsds,communication,file-transfer,packet,space
Classifier: Development Status :: 5 - Production/Stable
Classifier: License :: OSI Approved :: Apache Software License
Classifier: Natural Language :: English
Classifier: Operating System :: Microsoft :: Windows
Classifier: Operating System :: POSIX
Classifier: Programming Language :: Python :: 3
Classifier: Programming Language :: Python :: 3.9
Classifier: Programming Language :: Python :: 3.10
Classifier: Programming Language :: Python :: 3.11
Classifier: Programming Language :: Python :: 3.12
Classifier: Topic :: Communications
Classifier: Topic :: Scientific/Engineering
Classifier: Topic :: Software Development :: Libraries
Classifier: Topic :: Software Development :: Libraries :: Python Modules
Requires-Python: >=3.9
Requires-Dist: deprecation~=2.1
Requires-Dist: fastcrc~=0.3
Requires-Dist: spacepackets<0.32,>=0.30
Provides-Extra: lint
Requires-Dist: ruff; extra == 'lint'
Provides-Extra: test
Requires-Dist: coverage; extra == 'test'
Requires-Dist: pyfakefs~=5.2; extra == 'test'
Requires-Dist: pytest; extra == 'test'
